records.py
records_fork-0.5.5.dist-info/LICENSE
records_fork-0.5.5.dist-info/METADATA
records_fork-0.5.5.dist-info/WHEEL
records_fork-0.5.5.dist-info/entry_points.txt
records_fork-0.5.5.dist-info/top_level.txt
records_fork-0.5.5.dist-info/RECORD
